digcnv/CNVision.py
digcnv/DigCnvPreProcessing.py
digcnv/DigCnvTunning.py
digcnv/__init__.py
digcnv/__main__.py
digcnv/dataPreparation.py
digcnv/dataVerif.py
digcnv/digCNV_logger.py
digcnv/digCnvModel.py
digcnv/utils.py
digcnv/data/CNVision_format_merge_ukbb.pl
digcnv/data/Region_centromere_hg19.dat
digcnv/data/SegDup_filtres_Ok_Oct.map
digcnv-0.5.2.dist-info/LICENSE
digcnv-0.5.2.dist-info/METADATA
digcnv-0.5.2.dist-info/WHEEL
digcnv-0.5.2.dist-info/entry_points.txt
digcnv-0.5.2.dist-info/top_level.txt
digcnv-0.5.2.dist-info/RECORD
