Metadata-Version: 2.2
Name: digcnv
Version: 0.5.2
Summary: DigCNV: Discriminating True CNVs from artifacts from genotyping without further visualisation
Author-email: Thomas Renne <thomas.renne@umontreal.ca>
License:                     GNU GENERAL PUBLIC LICENSE
Project-URL: Homepage, https://github.com/labjacquemont/DigCNV
Keywords: cnv,quality control,machine learning,genotyping
Classifier: License :: OSI Approved :: GNU General Public License v3 or later (GPLv3+)
Classifier: Programming Language :: Python
Classifier: Programming Language :: Python :: 3
Classifier: Programming Language :: Perl
Classifier: Development Status :: 4 - Beta
Classifier: Environment :: Console
Classifier: Intended Audience :: Science/Research
Classifier: Natural Language :: English
Classifier: Operating System :: MacOS
Classifier: Operating System :: Microsoft
Classifier: Operating System :: Unix
Classifier: Topic :: Scientific/Engineering :: Bio-Informatics
Requires-Python: >=3.10.4
License-File: LICENSE
Requires-Dist: pandas
Requires-Dist: configparser
Requires-Dist: imbalanced-learn
Requires-Dist: scikit-learn
Requires-Dist: matplotlib
Requires-Dist: seaborn
Requires-Dist: joblib>=0.11
Provides-Extra: dev
Requires-Dist: pytest; extra == "dev"
